spatial_networks/__init__.py
spatial_networks/spatial_networks.py
spatial_networks/data/paris_subway.json
spatial_networks/utils/__init__.py
spatial_networks/utils/core_utils.py
spatial_networks/utils/generators.py
spatial_networks/utils/geometry_utils.py
spatial_networks/utils/graph_io.py
spatial_networks/utils/graph_utils.py
spatial_networks/utils/loaders.py
spatial_networks/utils/plot_utils.py
spatial_networks-0.0.9.dist-info/LICENSE
spatial_networks-0.0.9.dist-info/METADATA
spatial_networks-0.0.9.dist-info/WHEEL
spatial_networks-0.0.9.dist-info/top_level.txt
spatial_networks-0.0.9.dist-info/RECORD
